whippersnappy/Roboto-Regular.ttf
whippersnappy/__init__.py
whippersnappy/_version.py
whippersnappy/config_app.py
whippersnappy/core.py
whippersnappy/read_geometry.py
whippersnappy/types.py
whippersnappy/cli/__init__.py
whippersnappy/cli/whippersnap.py
whippersnappy/commands/__init__.py
whippersnappy/commands/sys_info.py
whippersnappy/utils/__init__.py
whippersnappy/utils/_config.py
whippersnappy-1.3.1.dist-info/licenses/LICENSE
whippersnappy-1.3.1.dist-info/METADATA
whippersnappy-1.3.1.dist-info/WHEEL
whippersnappy-1.3.1.dist-info/entry_points.txt
whippersnappy-1.3.1.dist-info/top_level.txt
whippersnappy-1.3.1.dist-info/RECORD
